mandarin_tamer/__init__.py
mandarin_tamer/mandarin_tamer.py
mandarin_tamer/conversion_dictionaries/__init__.py
mandarin_tamer/conversion_dictionaries/simp2simp/__init__.py
mandarin_tamer/conversion_dictionaries/simp2simp/modern_simp_chars.json
mandarin_tamer/conversion_dictionaries/simp2simp/modern_simp_one2many.json
mandarin_tamer/conversion_dictionaries/simp2simp/modern_simp_phrases.json
mandarin_tamer/conversion_dictionaries/simp2simp/norm_simp_chars.json
mandarin_tamer/conversion_dictionaries/simp2simp/norm_simp_one2many.json
mandarin_tamer/conversion_dictionaries/simp2simp/norm_simp_phrases.json
mandarin_tamer/conversion_dictionaries/simp2trad/__init__.py
mandarin_tamer/conversion_dictionaries/simp2trad/s2t_chars.json
mandarin_tamer/conversion_dictionaries/simp2trad/s2t_one2many.json
mandarin_tamer/conversion_dictionaries/simp2trad/s2t_phrases.json
mandarin_tamer/conversion_dictionaries/trad2simp/__init__.py
mandarin_tamer/conversion_dictionaries/trad2simp/t2s_chars.json
mandarin_tamer/conversion_dictionaries/trad2simp/t2s_one2many.json
mandarin_tamer/conversion_dictionaries/trad2simp/t2s_phrases.json
mandarin_tamer/conversion_dictionaries/trad2trad/__init__.py
mandarin_tamer/conversion_dictionaries/trad2trad/modern_trad_chars.json
mandarin_tamer/conversion_dictionaries/trad2trad/modern_trad_one2many.json
mandarin_tamer/conversion_dictionaries/trad2trad/modern_trad_phrases.json
mandarin_tamer/conversion_dictionaries/trad2trad/norm_trad_chars.json
mandarin_tamer/conversion_dictionaries/trad2trad/norm_trad_one2many.json
mandarin_tamer/conversion_dictionaries/trad2trad/norm_trad_phrases.json
mandarin_tamer/conversion_dictionaries/tw/__init__.py
mandarin_tamer/conversion_dictionaries/tw/t2tw_chars.json
mandarin_tamer/conversion_dictionaries/tw/t2tw_one2many.json
mandarin_tamer/conversion_dictionaries/tw/t2tw_phrases.json
mandarin_tamer/conversion_dictionaries/tw/tw2t_chars.json
mandarin_tamer/conversion_dictionaries/tw/tw2t_one2many.json
mandarin_tamer-0.0.11.dist-info/LICENSE
mandarin_tamer-0.0.11.dist-info/METADATA
mandarin_tamer-0.0.11.dist-info/WHEEL
mandarin_tamer-0.0.11.dist-info/top_level.txt
mandarin_tamer-0.0.11.dist-info/RECORD
