Metadata-Version: 2.2
Name: mandarin-tamer
Version: 0.0.11
Summary: MandarinTamer is a Python library for converting Mandarin text between Simplified Chinese and Traditional Chinese, with a focus on the Taiwanese variant. It's designed to be accurate, flexible, and easy to use.
Author-email: Jon Knebel <jonknebel@gmail.com>
License: MIT
Project-URL: Homepage, https://github.com/creolio/mandarinTamer
Project-URL: Issues, https://github.com/creolio/mandarinTamer/issues
Classifier: Programming Language :: Python :: 3
Classifier: Operating System :: OS Independent
Requires-Python: >=3.11
License-File: LICENSE
Requires-Dist: openai>=1.60.0
Requires-Dist: opencc>=1.1.9
Requires-Dist: opencc-python-reimplemented>=0.1.7
Requires-Dist: pypinyin>=0.51.0
